ObjDict-0.4.4.dist-info/DESCRIPTION.rst
ObjDict-0.4.4.dist-info/METADATA
ObjDict-0.4.4.dist-info/RECORD
ObjDict-0.4.4.dist-info/WHEEL
ObjDict-0.4.4.dist-info/entry_points.txt
ObjDict-0.4.4.dist-info/metadata.json
ObjDict-0.4.4.dist-info/top_level.txt
objdict/YM_CA.py
objdict/__init__.py
objdict/dualUrlJson.py
objdict/enums.py
objdict/inputs.py
objdict/objDict.py
objdict/pytestcode.py
objdict/struct.py
