Metadata-Version: 1.1
Name: ObjDict
Version: 0.4.4
Summary: The ObjDict class has many uses including: as a tool for processing and generating json information, for ad-hoc classes and mutable named tuples, or just as dictionaries that allow dot notation access.
Home-page: https://bitbucket.org/objdict/objdict
Author: Ian Ogilvy
Author-email: ian.ogilvy@saltmobile.com
License: LGPL
Keywords: object dictionary tuples namedtuples namedlists JSON custom classes
Platform: UNKNOWN
Classifier: Development Status :: 4 - Beta
Classifier: Intended Audience :: Developers
Classifier: Topic :: Software Development :: Libraries :: Python Modules
Classifier: Topic :: Utilities
Classifier: License :: OSI Approved :: GNU Library or Lesser General Public License (LGPL)
Classifier: Operating System :: OS Independent
Classifier: Programming Language :: Python :: 2
Classifier: Programming Language :: Python :: 2.7
Classifier: Programming Language :: Python :: 3
Classifier: Programming Language :: Python :: 3.2
Classifier: Programming Language :: Python :: 3.3
Classifier: Programming Language :: Python :: 3.4
Classifier: Programming Language :: Python :: 3.5
Classifier: Programming Language :: Python :: 3.6
